revos/__init__.py
revos/py.typed
revos/auth/__init__.py
revos/auth/core.py
revos/auth/exceptions.py
revos/auth/tokens.py
revos/config/__init__.py
revos/config/api.py
revos/config/env_parser.py
revos/config/factory.py
revos/config/llm.py
revos/config/llm_models.py
revos/config/logging.py
revos/config/main.py
revos/config/token.py
revos/legacy/__init__.py
revos/legacy/revo.py
revos/llm/__init__.py
revos/llm/tools.py
revos/tokens/__init__.py
revos/tokens/background.py
revos/tokens/manager.py
revos/tokens/observer.py
revos/tokens/refresh.py
revos-0.1.9.dist-info/licenses/LICENSE
revos-0.1.9.dist-info/METADATA
revos-0.1.9.dist-info/WHEEL
revos-0.1.9.dist-info/top_level.txt
revos-0.1.9.dist-info/RECORD
