Metadata-Version: 2.4
Name: revos
Version: 0.1.9
Summary: A Python library for LLM API authentication and LangChain-based LLM tools
Home-page: https://github.com/yourusername/revo
Author: Your Name
Author-email: Andras Gyacsok <your.email@example.com>
License-Expression: MIT
Project-URL: Homepage, https://github.com/kavodsky/revos
Project-URL: Repository, https://github.com/kavodsky/revos
Project-URL: Documentation, https://github.com/kavodsky/revos#readme
Project-URL: Bug Tracker, https://github.com/kavodsky/revos/issues
Keywords: revos,llm,langchain,authentication,token-management
Classifier: Development Status :: 3 - Alpha
Classifier: Intended Audience :: Developers
Classifier: Programming Language :: Python :: 3
Classifier: Programming Language :: Python :: 3.11
Classifier: Programming Language :: Python :: 3.12
Classifier: Topic :: Software Development :: Libraries :: Python Modules
Classifier: Topic :: Scientific/Engineering :: Artificial Intelligence
Requires-Python: >=3.11
License-File: LICENSE
Requires-Dist: requests>=2.31.0
Requires-Dist: httpx>=0.24.0
Requires-Dist: httpx-auth>=0.20.0
Requires-Dist: langchain-core>=0.1.0
Requires-Dist: langchain-openai>=0.1.0
Requires-Dist: pydantic>=2.0.0
Requires-Dist: pydantic-settings>=2.0.0
Requires-Dist: python-dotenv>=1.0.0
Provides-Extra: dev
Requires-Dist: pytest>=7.0.0; extra == "dev"
Requires-Dist: pytest-asyncio>=0.21.0; extra == "dev"
Requires-Dist: black>=23.0.0; extra == "dev"
Requires-Dist: isort>=5.12.0; extra == "dev"
Requires-Dist: flake8>=6.0.0; extra == "dev"
Requires-Dist: mypy>=1.0.0; extra == "dev"
Requires-Dist: mkdocs>=1.5.0; extra == "dev"
Requires-Dist: mkdocs-material>=9.0.0; extra == "dev"
Requires-Dist: mkdocstrings[python]>=0.24.0; extra == "dev"
Dynamic: author
Dynamic: home-page
Dynamic: license-file
Dynamic: requires-python
